[
  {
    "killmail_id": 130002258,
    "killmail_hash": "add49e8c2b9c4e36c524b1cfc692bf56cdc12e06",
    "kill_time": "2025-09-21T03:39:04Z",
    "ship_type_id": 20185,
    "ship_type_name": "Charon",
    "solar_system_id": 30003467,
    "solar_system_name": "Frulegur",
    "region_name": "Metropolis",
    "victim": {
      "character_id": 2123534288,
      "character_name": "Thodore Hammer",
      "corporation_id": 98803643,
      "corporation_name": "XANAX Withdrawal Corp.",
      "alliance_id": 99014167,
      "alliance_name": "XANAX Withdrawal Corp. Alliance"
    },
    "zkb_url": "https://zkillboard.com/kill/130002258/",
    "total_value": 2214895024.04,
    "final_attacker": {
      "character_name": "MystinaCC",
      "corporation_name": "Nekogame",
      "alliance_name": "COASTAL BROTHERHOOD",
      "ship_type_name": "Widow"
    }
  },
  {
    "killmail_id": 129994142,
    "killmail_hash": "5d8cdaed9d5579b97fb61bf29fecf8cfb89d3211",
    "kill_time": "2025-09-20T19:58:47Z",
    "ship_type_id": 20187,
    "ship_type_name": "Obelisk",
    "solar_system_id": 30002049,
    "solar_system_name": "Uttindar",
    "region_name": "Metropolis",
    "victim": {
      "character_id": 2114126535,
      "character_name": "Yrval Maldiran",
      "corporation_id": 98690534,
      "corporation_name": "Maldiran Inc.",
      "alliance_id": null,
      "alliance_name": null
    },
    "zkb_url": "https://zkillboard.com/kill/129994142/",
    "total_value": 4323539412.31,
    "final_attacker": {
      "character_name": "Pinch Hawk",
      "corporation_name": "Clipped Wingz",
      "alliance_name": "The Conference",
      "ship_type_name": "Catalyst"
    }
  },
  {
    "killmail_id": 129993308,
    "killmail_hash": "5266dd83586ffe91a72ae1b1ba18b160f8f6ead5",
    "kill_time": "2025-09-20T19:26:21Z",
    "ship_type_id": 20185,
    "ship_type_name": "Charon",
    "solar_system_id": 31000816,
    "solar_system_name": "J141637",
    "region_name": "B-R00008",
    "victim": {
      "character_id": 1228431467,
      "character_name": "CorrinoGiovanni",
      "corporation_id": 98650301,
      "corporation_name": "Triglavian Directive",
      "alliance_id": 99012723,
      "alliance_name": "S h a d o w"
    },
    "zkb_url": "https://zkillboard.com/kill/129993308/",
    "total_value": 1971961035.92,
    "final_attacker": {
      "character_name": "ZazaBinks",
      "corporation_name": "Credendo Vides",
      "alliance_name": "Khimi Harar",
      "ship_type_name": "Venture"
    }
  },
  {
    "killmail_id": 129992893,
    "killmail_hash": "4758143cb3b9e53b492e51fc96ca99867b02241a",
    "kill_time": "2025-09-20T19:08:22Z",
    "ship_type_id": 20185,
    "ship_type_name": "Charon",
    "solar_system_id": 30005196,
    "solar_system_name": "Ahbazon",
    "region_name": "Genesis",
    "victim": {
      "character_id": 2123709913,
      "character_name": "Sly Sensorspank",
      "corporation_id": 98785282,
      "corporation_name": "Militant Industrialists LLC",
      "alliance_id": 99013981,
      "alliance_name": "Militant Consortium"
    },
    "zkb_url": "https://zkillboard.com/kill/129992893/",
    "total_value": 2880514143.88,
    "final_attacker": {
      "character_name": "Aoife Divine",
      "corporation_name": "BlackCore Tactics",
      "alliance_name": "Ahbazon-Prime",
      "ship_type_name": "Oracle"
    }
  },
  {
    "killmail_id": 129991964,
    "killmail_hash": "c92fb76f77e4114d23fe0c47ef6225ff9e1ed142",
    "kill_time": "2025-09-20T18:23:40Z",
    "ship_type_id": 20187,
    "ship_type_name": "Obelisk",
    "solar_system_id": 30002791,
    "solar_system_name": "Sirppala",
    "region_name": "The Citadel",
    "victim": {
      "character_id": 909099883,
      "character_name": "Alex Cash",
      "corporation_id": 1275189296,
      "corporation_name": "Rearden Industrial Concern",
      "alliance_id": null,
      "alliance_name": null
    },
    "zkb_url": "https://zkillboard.com/kill/129991964/",
    "total_value": 18531312757.74,
    "final_attacker": {
      "character_name": "lndia",
      "corporation_name": "Center for Advanced Studies",
      "alliance_name": null,
      "ship_type_name": "Cenotaph"
    }
  },
  {
    "killmail_id": 129990927,
    "killmail_hash": "400eb04f7cdff4d0e4a5e363a240a18262bc0aaf",
    "kill_time": "2025-09-20T17:45:06Z",
    "ship_type_id": 20187,
    "ship_type_name": "Obelisk",
    "solar_system_id": 30002049,
    "solar_system_name": "Uttindar",
    "region_name": "Metropolis",
    "victim": {
      "character_id": 95759614,
      "character_name": "Alix Diamond",
      "corporation_id": 1000168,
      "corporation_name": "Federal Navy Academy",
      "alliance_id": null,
      "alliance_name": null
    },
    "zkb_url": "https://zkillboard.com/kill/129990927/",
    "total_value": 9296148877.3,
    "final_attacker": {
      "character_name": "Fuming Hawk",
      "corporation_name": "Clipped Wingz",
      "alliance_name": "The Conference",
      "ship_type_name": "Hound"
    }
  },
  {
    "killmail_id": 129989010,
    "killmail_hash": "6fd34cd5d6a1de9c478099290aef91b56b9ebdf0",
    "kill_time": "2025-09-20T16:03:33Z",
    "ship_type_id": 20185,
    "ship_type_name": "Charon",
    "solar_system_id": 30002049,
    "solar_system_name": "Uttindar",
    "region_name": "Metropolis",
    "victim": {
      "character_id": 2113479631,
      "character_name": "Edart Eistiras",
      "corporation_id": 98811387,
      "corporation_name": "Dot Dot Astericks",
      "alliance_id": 99005100,
      "alliance_name": "All My Friends Are Ded"
    },
    "zkb_url": "https://zkillboard.com/kill/129989010/",
    "total_value": 2799216129.9,
    "final_attacker": {
      "character_name": "Fool Hawk",
      "corporation_name": "Clipped Wingz",
      "alliance_name": "The Conference",
      "ship_type_name": "Catalyst"
    }
  },
  {
    "killmail_id": 129984459,
    "killmail_hash": "cf0dc6e64d9439f7958052e0f59492652d539d51",
    "kill_time": "2025-09-20T12:15:32Z",
    "ship_type_id": 20187,
    "ship_type_name": "Obelisk",
    "solar_system_id": 30002769,
    "solar_system_name": "Enderailen",
    "region_name": "The Citadel",
    "victim": {
      "character_id": 2038557451,
      "character_name": "Kaeric",
      "corporation_id": 98662323,
      "corporation_name": "Voidhounds",
      "alliance_id": 99010756,
      "alliance_name": "Pretenders"
    },
    "zkb_url": "https://zkillboard.com/kill/129984459/",
    "total_value": 7720976526.03,
    "final_attacker": {
      "character_name": "Bryan Yakinov",
      "corporation_name": "Lowlife.",
      "alliance_name": "Snuffed Out",
      "ship_type_name": "Panther"
    }
  },
  {
    "killmail_id": 129982939,
    "killmail_hash": "fe14ca57eb57ddbb4a66e3375624f2fe122eb409",
    "kill_time": "2025-09-20T09:56:24Z",
    "ship_type_id": 20189,
    "ship_type_name": "Fenrir",
    "solar_system_id": 30003470,
    "solar_system_name": "Odebeinn",
    "region_name": "Metropolis",
    "victim": {
      "character_id": 91606327,
      "character_name": "Hungree Wolf",
      "corporation_id": 1000046,
      "corporation_name": "Sebiestor Tribe",
      "alliance_id": null,
      "alliance_name": null
    },
    "zkb_url": "https://zkillboard.com/kill/129982939/",
    "total_value": 2048776373.97,
    "final_attacker": {
      "character_name": "l am Gundam",
      "corporation_name": "Kiddy Girl-and",
      "alliance_name": "COASTAL BROTHERHOOD",
      "ship_type_name": "Cenotaph"
    }
  },
  {
    "killmail_id": 129982425,
    "killmail_hash": "a025f1cd9ca2d26db43890c5f82005f013e93c87",
    "kill_time": "2025-09-20T09:11:55Z",
    "ship_type_id": 28850,
    "ship_type_name": "Ark",
    "solar_system_id": 30001390,
    "solar_system_name": "Pakkonen",
    "region_name": "Lonetrek",
    "victim": {
      "character_id": 1093485810,
      "character_name": "Samuel Samper",
      "corporation_id": 644716789,
      "corporation_name": "Decadence.",
      "alliance_id": 741557221,
      "alliance_name": "RAZOR Alliance"
    },
    "zkb_url": "https://zkillboard.com/kill/129982425/",
    "total_value": 9580426344.37,
    "final_attacker": {
      "character_name": "Coyote Benihime",
      "corporation_name": "The Ruckus",
      "alliance_name": null,
      "ship_type_name": "Panther"
    }
  },
  {
    "killmail_id": 129982118,
    "killmail_hash": "d647a0dd1f030789a08e12bf225e6b552d278ad5",
    "kill_time": "2025-09-20T08:48:48Z",
    "ship_type_id": 28844,
    "ship_type_name": "Rhea",
    "solar_system_id": 30000889,
    "solar_system_name": "XD-TOV",
    "region_name": "Tribute",
    "victim": {
      "character_id": 1591938075,
      "character_name": "Ricardos Fordisimo",
      "corporation_id": 98679428,
      "corporation_name": "SCREECHING GRASS",
      "alliance_id": 99010320,
      "alliance_name": "Bully Brigade"
    },
    "zkb_url": "https://zkillboard.com/kill/129982118/",
    "total_value": 9641946250.11,
    "final_attacker": {
      "character_name": "Reda Astao Makanen",
      "corporation_name": "Aurora Empire",
      "alliance_name": "Brotherhood of Spacers",
      "ship_type_name": "Redeemer"
    }
  },
  {
    "killmail_id": 129981054,
    "killmail_hash": "6c96d528376d4f39d9b5ae9dfb1252155590b978",
    "kill_time": "2025-09-20T07:20:46Z",
    "ship_type_id": 20185,
    "ship_type_name": "Charon",
    "solar_system_id": 30000144,
    "solar_system_name": "Perimeter",
    "region_name": "The Forge",
    "victim": {
      "character_id": 2120888059,
      "character_name": "Dedritte Thiesant",
      "corporation_id": 98786884,
      "corporation_name": "Naughty Badger Supply CO",
      "alliance_id": null,
      "alliance_name": null
    },
    "zkb_url": "https://zkillboard.com/kill/129981054/",
    "total_value": 4865662005.93,
    "final_attacker": {
      "character_name": "zViperz3",
      "corporation_name": "URSA PRIMUS",
      "alliance_name": "URSA.",
      "ship_type_name": "Cenotaph"
    }
  },
  {
    "killmail_id": 129980262,
    "killmail_hash": "a5dcf4588cf2e8f775c775a7cba859877b30e2f9",
    "kill_time": "2025-09-20T06:10:56Z",
    "ship_type_id": 81040,
    "ship_type_name": "Avalanche",
    "solar_system_id": 30003523,
    "solar_system_name": "Hama",
    "region_name": "Domain",
    "victim": {
      "character_id": 2115841152,
      "character_name": "Amar Kring",
      "corporation_id": 98224835,
      "corporation_name": "Star Nation",
      "alliance_id": 99003214,
      "alliance_name": "Brave Collective"
    },
    "zkb_url": "https://zkillboard.com/kill/129980262/",
    "total_value": 2227854620.04,
    "final_attacker": {
      "character_name": "TsunamiXoX",
      "corporation_name": "EVE Kindergarten",
      "alliance_name": null,
      "ship_type_name": "Cenotaph"
    }
  },
  {
    "killmail_id": 129979648,
    "killmail_hash": "abca44cc3c154b5c0b0acc03037337a3f671441a",
    "kill_time": "2025-09-20T05:27:35Z",
    "ship_type_id": 20185,
    "ship_type_name": "Charon",
    "solar_system_id": 30000240,
    "solar_system_name": "4-HWWF",
    "region_name": "Vale of the Silent",
    "victim": {
      "character_id": 2113639241,
      "character_name": "MoonScape",
      "corporation_id": 98562360,
      "corporation_name": "My Little Pony.",
      "alliance_id": 99003581,
      "alliance_name": "Fraternity."
    },
    "zkb_url": "https://zkillboard.com/kill/129979648/",
    "total_value": 6974611609.92,
    "final_attacker": {
      "character_name": "Jon Illat",
      "corporation_name": "Worthless Carebears",
      "alliance_name": "The Initiative.",
      "ship_type_name": "Hound"
    }
  },
  {
    "killmail_id": 129978944,
    "killmail_hash": "b1ddc67d036ef6c707375222741dbafa0f593a18",
    "kill_time": "2025-09-20T04:34:36Z",
    "ship_type_id": 20187,
    "ship_type_name": "Obelisk",
    "solar_system_id": 30002049,
    "solar_system_name": "Uttindar",
    "region_name": "Metropolis",
    "victim": {
      "character_id": 2114498503,
      "character_name": "Thorn of Justice",
      "corporation_id": 98470854,
      "corporation_name": "Airaria",
      "alliance_id": null,
      "alliance_name": null
    },
    "zkb_url": "https://zkillboard.com/kill/129978944/",
    "total_value": 4896511925.95,
    "final_attacker": {
      "character_name": "Hostile Hawk",
      "corporation_name": "Clipped Wingz",
      "alliance_name": "The Conference",
      "ship_type_name": "Catalyst"
    }
  },
  {
    "killmail_id": 129977228,
    "killmail_hash": "2d7dadb6b13b08a463994d65f9fa766c63765788",
    "kill_time": "2025-09-20T02:32:59Z",
    "ship_type_id": 81040,
    "ship_type_name": "Avalanche",
    "solar_system_id": 30001388,
    "solar_system_name": "Mara",
    "region_name": "Lonetrek",
    "victim": {
      "character_id": 543080636,
      "character_name": "Odarra",
      "corporation_id": 98810444,
      "corporation_name": "Loxmenardi's Forge",
      "alliance_id": null,
      "alliance_name": null
    },
    "zkb_url": "https://zkillboard.com/kill/129977228/",
    "total_value": 24118542043.46,
    "final_attacker": {
      "character_name": "Zadraxis",
      "corporation_name": "The Ruckus",
      "alliance_name": null,
      "ship_type_name": "Redeemer"
    }
  },
  {
    "killmail_id": 129976811,
    "killmail_hash": "af7e6f3b78fe93917bfb74e2a03676003ad4b923",
    "kill_time": "2025-09-20T02:12:44Z",
    "ship_type_id": 20183,
    "ship_type_name": "Providence",
    "solar_system_id": 30002972,
    "solar_system_name": "Gheth",
    "region_name": "Devoid",
    "victim": {
      "character_id": 1819685886,
      "character_name": "Alphablaster",
      "corporation_id": 732773091,
      "corporation_name": "Di-Tron Heavy Industries",
      "alliance_id": 99012982,
      "alliance_name": "OnlyFleets."
    },
    "zkb_url": "https://zkillboard.com/kill/129976811/",
    "total_value": 4517038577.26,
    "final_attacker": {
      "character_name": "Beige'Crayon",
      "corporation_name": "Box of Colors",
      "alliance_name": "The Conference",
      "ship_type_name": "Catalyst"
    }
  },
  {
    "killmail_id": 129976052,
    "killmail_hash": "874262fcb9c6b8dc9f91df5ec6c1a80142ab7a8c",
    "kill_time": "2025-09-20T01:24:12Z",
    "ship_type_id": 20187,
    "ship_type_name": "Obelisk",
    "solar_system_id": 30002049,
    "solar_system_name": "Uttindar",
    "region_name": "Metropolis",
    "victim": {
      "character_id": 95719758,
      "character_name": "Mitzelpik",
      "corporation_id": 1000168,
      "corporation_name": "Federal Navy Academy",
      "alliance_id": null,
      "alliance_name": null
    },
    "zkb_url": "https://zkillboard.com/kill/129976052/",
    "total_value": 17152738061.51,
    "final_attacker": {
      "character_name": "Larson Hawk",
      "corporation_name": "Clipped Wingz",
      "alliance_name": "The Conference",
      "ship_type_name": "Catalyst"
    }
  },
  {
    "killmail_id": 129972143,
    "killmail_hash": "f18282a0ecdf630079bb32404adb936b99bd0aa8",
    "kill_time": "2025-09-19T21:32:23Z",
    "ship_type_id": 28850,
    "ship_type_name": "Ark",
    "solar_system_id": 30001385,
    "solar_system_name": "Jan",
    "region_name": "Lonetrek",
    "victim": {
      "character_id": 1953308279,
      "character_name": "HandyMD",
      "corporation_id": 98390391,
      "corporation_name": "Jolly Roger's",
      "alliance_id": 99005100,
      "alliance_name": "All My Friends Are Ded"
    },
    "zkb_url": "https://zkillboard.com/kill/129972143/",
    "total_value": 10535341212.74,
    "final_attacker": {
      "character_name": "Dean Gabos",
      "corporation_name": "Lowlife.",
      "alliance_name": "Snuffed Out",
      "ship_type_name": "Redeemer"
    }
  },
  {
    "killmail_id": 129970184,
    "killmail_hash": "ebb99b670b3f90bfe4c5a36a8b1c93403e88092f",
    "kill_time": "2025-09-19T20:07:55Z",
    "ship_type_id": 34328,
    "ship_type_name": "Bowhead",
    "solar_system_id": 30002756,
    "solar_system_name": "Ishomilken",
    "region_name": "The Citadel",
    "victim": {
      "character_id": 2115165273,
      "character_name": "elafloes Terona",
      "corporation_id": 98595253,
      "corporation_name": "Absolute Order II",
      "alliance_id": 99010386,
      "alliance_name": "Absolute Honor"
    },
    "zkb_url": "https://zkillboard.com/kill/129970184/",
    "total_value": 1961751876.01,
    "final_attacker": {
      "character_name": "Fyrsta",
      "corporation_name": "Lowlife.",
      "alliance_name": "Snuffed Out",
      "ship_type_name": "Panther"
    }
  },
  {
    "killmail_id": 129969483,
    "killmail_hash": "5d3242671b7c3a0a199e83e77e456923a1fdd844",
    "kill_time": "2025-09-19T19:43:55Z",
    "ship_type_id": 20185,
    "ship_type_name": "Charon",
    "solar_system_id": 30001389,
    "solar_system_name": "Isanamo",
    "region_name": "Lonetrek",
    "victim": {
      "character_id": 1721390566,
      "character_name": "Kiroven Kunnin",
      "corporation_id": 671183163,
      "corporation_name": "Lockheed Martin Inc.",
      "alliance_id": null,
      "alliance_name": null
    },
    "zkb_url": "https://zkillboard.com/kill/129969483/",
    "total_value": 2920286175.08,
    "final_attacker": {
      "character_name": "Zacharias Zachanassian",
      "corporation_name": "The Dark Space Initiative",
      "alliance_name": "Scary Wormhole People",
      "ship_type_name": "Vargur"
    }
  },
  {
    "killmail_id": 129968760,
    "killmail_hash": "d2df0aff89bffb484a97a68a7ffc774902adee21",
    "kill_time": "2025-09-19T19:15:48Z",
    "ship_type_id": 20187,
    "ship_type_name": "Obelisk",
    "solar_system_id": 31001718,
    "solar_system_name": "J163217",
    "region_name": "D-R00021",
    "victim": {
      "character_id": 469010279,
      "character_name": "Christopher Sim",
      "corporation_id": 98560621,
      "corporation_name": "Violence is the Answer",
      "alliance_id": null,
      "alliance_name": null
    },
    "zkb_url": "https://zkillboard.com/kill/129968760/",
    "total_value": 2223242504.21,
    "final_attacker": {
      "character_name": "Egerek",
      "corporation_name": "Mental Disruption",
      "alliance_name": null,
      "ship_type_name": "Absolution"
    }
  },
  {
    "killmail_id": 129960999,
    "killmail_hash": "97e6b6b32537d48dd276e96bf8e5917ddbb4d657",
    "kill_time": "2025-09-19T11:51:47Z",
    "ship_type_id": 28846,
    "ship_type_name": "Nomad",
    "solar_system_id": 30004246,
    "solar_system_name": "Vehan",
    "region_name": "Aridia",
    "victim": {
      "character_id": 2122254173,
      "character_name": "Sin Nombre Cool",
      "corporation_id": 98006194,
      "corporation_name": "Quarks LLC",
      "alliance_id": 99014081,
      "alliance_name": "Synergy of Support"
    },
    "zkb_url": "https://zkillboard.com/kill/129960999/",
    "total_value": 13488954884.07,
    "final_attacker": {
      "character_name": "Tony Sparx",
      "corporation_name": "RadioActivia",
      "alliance_name": "LowSechnaya Sholupen",
      "ship_type_name": "Wyvern"
    }
  },
  {
    "killmail_id": 129955221,
    "killmail_hash": "bc749e9abe191610e0ca4cd087e75520c0399ac6",
    "kill_time": "2025-09-19T01:56:50Z",
    "ship_type_id": 20185,
    "ship_type_name": "Charon",
    "solar_system_id": 30002972,
    "solar_system_name": "Gheth",
    "region_name": "Devoid",
    "victim": {
      "character_id": 2123392583,
      "character_name": "xupinfleet",
      "corporation_id": 98804712,
      "corporation_name": "XUP Corporation",
      "alliance_id": null,
      "alliance_name": null
    },
    "zkb_url": "https://zkillboard.com/kill/129955221/",
    "total_value": 9646106712.8,
    "final_attacker": {
      "character_name": "Cyan'Crayon",
      "corporation_name": "Box of Colors",
      "alliance_name": "The Conference",
      "ship_type_name": "Catalyst"
    }
  },
  {
    "killmail_id": 129954154,
    "killmail_hash": "18c5a889ddfd987d998bc0e621568b9d2d215657",
    "kill_time": "2025-09-19T00:32:54Z",
    "ship_type_id": 20187,
    "ship_type_name": "Obelisk",
    "solar_system_id": 30002792,
    "solar_system_name": "Irjunen",
    "region_name": "The Citadel",
    "victim": {
      "character_id": 909099883,
      "character_name": "Alex Cash",
      "corporation_id": 1275189296,
      "corporation_name": "Rearden Industrial Concern",
      "alliance_id": null,
      "alliance_name": null
    },
    "zkb_url": "https://zkillboard.com/kill/129954154/",
    "total_value": 18971454072.15,
    "final_attacker": {
      "character_name": "lndia",
      "corporation_name": "Center for Advanced Studies",
      "alliance_name": null,
      "ship_type_name": "Cenotaph"
    }
  },
  {
    "killmail_id": 129952934,
    "killmail_hash": "e3de5824cbe275d403cac66c1d16d1dd98c0fd20",
    "kill_time": "2025-09-18T22:13:59Z",
    "ship_type_id": 20185,
    "ship_type_name": "Charon",
    "solar_system_id": 30003729,
    "solar_system_name": "KBP7-G",
    "region_name": "Providence",
    "victim": {
      "character_id": 95866480,
      "character_name": "burning gizilian",
      "corporation_id": 98729619,
      "corporation_name": "Wealthy Tax Fugitives",
      "alliance_id": 99010240,
      "alliance_name": "The Curatores Veritatis Auxiliary"
    },
    "zkb_url": "https://zkillboard.com/kill/129952934/",
    "total_value": 2962999142.39,
    "final_attacker": {
      "character_name": "Lilithena Erquilenne",
      "corporation_name": "Suddenly a Covert Cyno",
      "alliance_name": "Honorable Third Party",
      "ship_type_name": "Redeemer"
    }
  },
  {
    "killmail_id": 129950321,
    "killmail_hash": "cc3f2234aee3acc3e57e3aec8ce4a00faaeee1e2",
    "kill_time": "2025-09-18T19:47:32Z",
    "ship_type_id": 20185,
    "ship_type_name": "Charon",
    "solar_system_id": 30002813,
    "solar_system_name": "Tama",
    "region_name": "The Citadel",
    "victim": {
      "character_id": 1882855030,
      "character_name": "DavidYanko",
      "corporation_id": 1000009,
      "corporation_name": "Caldari Provisions",
      "alliance_id": null,
      "alliance_name": null
    },
    "zkb_url": "https://zkillboard.com/kill/129950321/",
    "total_value": 1980259996.09,
    "final_attacker": {
      "character_name": "Mila Yakinov",
      "corporation_name": "Lowlife.",
      "alliance_name": "Snuffed Out",
      "ship_type_name": "Redeemer"
    }
  },
  {
    "killmail_id": 129945510,
    "killmail_hash": "af8194ffc4893a36ae47c7a9d95a02d160f279eb",
    "kill_time": "2025-09-18T14:32:20Z",
    "ship_type_id": 20183,
    "ship_type_name": "Providence",
    "solar_system_id": 30003488,
    "solar_system_name": "Penirgman",
    "region_name": "Domain",
    "victim": {
      "character_id": 2122908381,
      "character_name": "Logistic Panala 1",
      "corporation_id": 98753522,
      "corporation_name": "Tri-Tachyon Indy",
      "alliance_id": 99009824,
      "alliance_name": "Domain Research and Mining Inst. Logistics"
    },
    "zkb_url": "https://zkillboard.com/kill/129945510/",
    "total_value": 10667303764.72,
    "final_attacker": {
      "character_name": "lndia",
      "corporation_name": "Center for Advanced Studies",
      "alliance_name": null,
      "ship_type_name": "Cenotaph"
    }
  },
  {
    "killmail_id": 129943815,
    "killmail_hash": "60fea51e2b90476073468dd7ef8873a2408dc792",
    "kill_time": "2025-09-18T13:00:20Z",
    "ship_type_id": 28850,
    "ship_type_name": "Ark",
    "solar_system_id": 30003209,
    "solar_system_name": "R8WV-7",
    "region_name": "Oasa",
    "victim": {
      "character_id": 2115284985,
      "character_name": "detective spider",
      "corporation_id": 98631475,
      "corporation_name": "Profane Proverb",
      "alliance_id": 99005338,
      "alliance_name": "Pandemic Horde"
    },
    "zkb_url": "https://zkillboard.com/kill/129943815/",
    "total_value": 9505928921.91,
    "final_attacker": {
      "character_name": "Wheezus1995",
      "corporation_name": "Pimpdynamics V",
      "alliance_name": "Monochrome Knights",
      "ship_type_name": "Hel"
    }
  },
  {
    "killmail_id": 129942062,
    "killmail_hash": "7dc1f92e808bac736c6f1faeb4c970c6d184ec3e",
    "kill_time": "2025-09-18T10:26:06Z",
    "ship_type_id": 20187,
    "ship_type_name": "Obelisk",
    "solar_system_id": 30002719,
    "solar_system_name": "Miroitem",
    "region_name": "Sinq Laison",
    "victim": {
      "character_id": 2123766399,
      "character_name": "Pencesine Pellion",
      "corporation_id": 1000169,
      "corporation_name": "Center for Advanced Studies",
      "alliance_id": null,
      "alliance_name": null
    },
    "zkb_url": "https://zkillboard.com/kill/129942062/",
    "total_value": 2236019460.82,
    "final_attacker": {
      "character_name": "chung moo",
      "corporation_name": "Best Kept Dunked",
      "alliance_name": "OnlyFleets.",
      "ship_type_name": "Typhoon"
    }
  },
  {
    "killmail_id": 129937179,
    "killmail_hash": "e74ec1a2eb990cab17458d093fc8752182de0b24",
    "kill_time": "2025-09-18T01:36:45Z",
    "ship_type_id": 20185,
    "ship_type_name": "Charon",
    "solar_system_id": 30003729,
    "solar_system_name": "KBP7-G",
    "region_name": "Providence",
    "victim": {
      "character_id": 2121177191,
      "character_name": "Dimitri Nemura",
      "corporation_id": 98630616,
      "corporation_name": "Absolute Order IV",
      "alliance_id": 99010386,
      "alliance_name": "Absolute Honor"
    },
    "zkb_url": "https://zkillboard.com/kill/129937179/",
    "total_value": 1973743526.29,
    "final_attacker": {
      "character_name": "Meiqur Orez",
      "corporation_name": "Trillium Invariant",
      "alliance_name": "Honorable Third Party",
      "ship_type_name": "Redeemer"
    }
  },
  {
    "killmail_id": 129935197,
    "killmail_hash": "4663b7c291d33b93895cfa9db013968d765d3bf6",
    "kill_time": "2025-09-17T22:29:04Z",
    "ship_type_id": 20185,
    "ship_type_name": "Charon",
    "solar_system_id": 30002187,
    "solar_system_name": "Amarr",
    "region_name": "Domain",
    "victim": {
      "character_id": 2122604802,
      "character_name": "2 Dragons",
      "corporation_id": 98006194,
      "corporation_name": "Quarks LLC",
      "alliance_id": 99014081,
      "alliance_name": "Synergy of Support"
    },
    "zkb_url": "https://zkillboard.com/kill/129935197/",
    "total_value": 12322054733.67,
    "final_attacker": {
      "character_name": "JuIi3t",
      "corporation_name": "State War Academy",
      "alliance_name": null,
      "ship_type_name": "Cenotaph"
    }
  },
  {
    "killmail_id": 129933227,
    "killmail_hash": "9cb4e770a00e33418c567464298d13b8f0f6519a",
    "kill_time": "2025-09-17T20:20:56Z",
    "ship_type_id": 20185,
    "ship_type_name": "Charon",
    "solar_system_id": 30000142,
    "solar_system_name": "Jita",
    "region_name": "The Forge",
    "victim": {
      "character_id": 92360371,
      "character_name": "Pure L'Ynori",
      "corporation_id": 98637328,
      "corporation_name": "Special Finance Section",
      "alliance_id": null,
      "alliance_name": null
    },
    "zkb_url": "https://zkillboard.com/kill/129933227/",
    "total_value": 4785327757.26,
    "final_attacker": {
      "character_name": "Marley Murderface",
      "corporation_name": "Slavers Union",
      "alliance_name": "Something Really Pretentious",
      "ship_type_name": "Cenotaph"
    }
  },
  {
    "killmail_id": 129931035,
    "killmail_hash": "fbdef3a20d8a8c0fe548c39e0f7933fb5dae8ac5",
    "kill_time": "2025-09-17T18:26:57Z",
    "ship_type_id": 34328,
    "ship_type_name": "Bowhead",
    "solar_system_id": 30001398,
    "solar_system_name": "Aunenen",
    "region_name": "Lonetrek",
    "victim": {
      "character_id": 2119677259,
      "character_name": "Aakman Brekka",
      "corporation_id": 98727604,
      "corporation_name": "BasementDwellers INC.",
      "alliance_id": null,
      "alliance_name": null
    },
    "zkb_url": "https://zkillboard.com/kill/129931035/",
    "total_value": 2710843464.09,
    "final_attacker": {
      "character_name": "Edgy Shadow-Lord",
      "corporation_name": "Deaths Shitposters",
      "alliance_name": "I have a jar of relish I cant open",
      "ship_type_name": "Redeemer"
    }
  },
  {
    "killmail_id": 129927406,
    "killmail_hash": "d3d4bcf70a73347bb7e3d71a081194c4e554a151",
    "kill_time": "2025-09-17T14:27:45Z",
    "ship_type_id": 20187,
    "ship_type_name": "Obelisk",
    "solar_system_id": 30002765,
    "solar_system_name": "Sivala",
    "region_name": "The Citadel",
    "victim": {
      "character_id": 606524367,
      "character_name": "freerambler",
      "corporation_id": 98698983,
      "corporation_name": "Scan Stakan",
      "alliance_id": 99012122,
      "alliance_name": "HOLD MY PROBS"
    },
    "zkb_url": "https://zkillboard.com/kill/129927406/",
    "total_value": 8682133545.53,
    "final_attacker": {
      "character_name": "Ch4rli3",
      "corporation_name": "R.E.M.N.A.N.T.S",
      "alliance_name": null,
      "ship_type_name": "Talos"
    }
  },
  {
    "killmail_id": 129917481,
    "killmail_hash": "0d6e2babecaf7efb2c36fa099687a3f17c26d2fc",
    "kill_time": "2025-09-16T21:15:45Z",
    "ship_type_id": 20185,
    "ship_type_name": "Charon",
    "solar_system_id": 30000142,
    "solar_system_name": "Jita",
    "region_name": "The Forge",
    "victim": {
      "character_id": 1495777134,
      "character_name": "blu movie",
      "corporation_id": 98793036,
      "corporation_name": "Goats A'hoy - Miners Of The Deep",
      "alliance_id": 99013803,
      "alliance_name": "Wicked Goats Enterprises"
    },
    "zkb_url": "https://zkillboard.com/kill/129917481/",
    "total_value": 10924081908.41,
    "final_attacker": {
      "character_name": "Mona Murderface",
      "corporation_name": "Slavers Union",
      "alliance_name": "Something Really Pretentious",
      "ship_type_name": "Cenotaph"
    }
  },
  {
    "killmail_id": 129914994,
    "killmail_hash": "a413eb3390d03be68718162ad372dafa478dc28d",
    "kill_time": "2025-09-16T18:45:57Z",
    "ship_type_id": 20187,
    "ship_type_name": "Obelisk",
    "solar_system_id": 30000156,
    "solar_system_name": "Josameto",
    "region_name": "The Forge",
    "victim": {
      "character_id": 1792921127,
      "character_name": "Puddyfoot",
      "corporation_id": 1000169,
      "corporation_name": "Center for Advanced Studies",
      "alliance_id": null,
      "alliance_name": null
    },
    "zkb_url": "https://zkillboard.com/kill/129914994/",
    "total_value": 6886816030.06,
    "final_attacker": {
      "character_name": "Little Miss Scary",
      "corporation_name": "Midget Mafia Contract Crew",
      "alliance_name": "Novus Ordo.",
      "ship_type_name": "Talos"
    }
  },
  {
    "killmail_id": 129908326,
    "killmail_hash": "3d40a3c6f0b5f16a548aa2370a1f01c8a9a17d3d",
    "kill_time": "2025-09-16T10:16:46Z",
    "ship_type_id": 20187,
    "ship_type_name": "Obelisk",
    "solar_system_id": 30005022,
    "solar_system_name": "Ane",
    "region_name": "Essence",
    "victim": {
      "character_id": 2119962023,
      "character_name": "Ignaves Nardieu",
      "corporation_id": 98746955,
      "corporation_name": "Light Spectrum Specialties",
      "alliance_id": null,
      "alliance_name": null
    },
    "zkb_url": "https://zkillboard.com/kill/129908326/",
    "total_value": 2252203689.71,
    "final_attacker": {
      "character_name": "Joshua Kurvore",
      "corporation_name": "Sons of Seyllin",
      "alliance_name": "Pirate Lords of War",
      "ship_type_name": "Golem"
    }
  },
  {
    "killmail_id": 129898945,
    "killmail_hash": "4fdd3da7ea95fe05cc0a05351566c481f463f59f",
    "kill_time": "2025-09-15T19:56:20Z",
    "ship_type_id": 34328,
    "ship_type_name": "Bowhead",
    "solar_system_id": 30002282,
    "solar_system_name": "Bhizheba",
    "region_name": "Domain",
    "victim": {
      "character_id": 2117761763,
      "character_name": "Kengy",
      "corporation_id": 98642731,
      "corporation_name": "Felidae Fleet",
      "alliance_id": null,
      "alliance_name": null
    },
    "zkb_url": "https://zkillboard.com/kill/129898945/",
    "total_value": 3937980273.99,
    "final_attacker": {
      "character_name": "Asuna Aboshi",
      "corporation_name": "Black Ashes",
      "alliance_name": null,
      "ship_type_name": "Cerberus"
    }
  },
  {
    "killmail_id": 129897230,
    "killmail_hash": "c779d8e8082c7635b7bb6e67e99c2ebc32aa7403",
    "kill_time": "2025-09-15T18:47:41Z",
    "ship_type_id": 20185,
    "ship_type_name": "Charon",
    "solar_system_id": 30002776,
    "solar_system_name": "Annaro",
    "region_name": "The Citadel",
    "victim": {
      "character_id": 921353581,
      "character_name": "Willi deVille",
      "corporation_id": 376181252,
      "corporation_name": "House of Sins",
      "alliance_id": 99012089,
      "alliance_name": "Silent Nova"
    },
    "zkb_url": "https://zkillboard.com/kill/129897230/",
    "total_value": 25186743202.23,
    "final_attacker": {
      "character_name": "Mona Murderface",
      "corporation_name": "Slavers Union",
      "alliance_name": "Something Really Pretentious",
      "ship_type_name": "Cenotaph"
    }
  },
  {
    "killmail_id": 129896447,
    "killmail_hash": "00ad40f42598b35b464a1d77aade2314ce779176",
    "kill_time": "2025-09-15T18:01:37Z",
    "ship_type_id": 20189,
    "ship_type_name": "Fenrir",
    "solar_system_id": 30002390,
    "solar_system_name": "Heild",
    "region_name": "Molden Heath",
    "victim": {
      "character_id": 206938997,
      "character_name": "TIDYHOE",
      "corporation_id": 98788569,
      "corporation_name": "Independent Chamber of Unstable Misfits",
      "alliance_id": null,
      "alliance_name": null
    },
    "zkb_url": "https://zkillboard.com/kill/129896447/",
    "total_value": 2112396199.41,
    "final_attacker": {
      "character_name": "VoidRain",
      "corporation_name": "Tiamat Malediction",
      "alliance_name": "Parallaxis Alliance",
      "ship_type_name": "Redeemer"
    }
  },
  {
    "killmail_id": 129895217,
    "killmail_hash": "64ca25811da5abbe11ef35793d44b8d105b88208",
    "kill_time": "2025-09-15T16:51:39Z",
    "ship_type_id": 20187,
    "ship_type_name": "Obelisk",
    "solar_system_id": 30000142,
    "solar_system_name": "Jita",
    "region_name": "The Forge",
    "victim": {
      "character_id": 2121102787,
      "character_name": "Puksen Otsada",
      "corporation_id": 98750909,
      "corporation_name": "Voidbringer Logistics",
      "alliance_id": null,
      "alliance_name": null
    },
    "zkb_url": "https://zkillboard.com/kill/129895217/",
    "total_value": 8735485447.04,
    "final_attacker": {
      "character_name": "Faylee Freir",
      "corporation_name": "Abusing Game Mechanics",
      "alliance_name": null,
      "ship_type_name": "Cenotaph"
    }
  },
  {
    "killmail_id": 129891446,
    "killmail_hash": "ac02c3039c317e477bdaa945408af324f3bf47aa",
    "kill_time": "2025-09-15T12:43:28Z",
    "ship_type_id": 20183,
    "ship_type_name": "Providence",
    "solar_system_id": 30002686,
    "solar_system_name": "Olettiers",
    "region_name": "Sinq Laison",
    "victim": {
      "character_id": 2121436914,
      "character_name": "Losing isk69",
      "corporation_id": 98448738,
      "corporation_name": "Q-Zar",
      "alliance_id": 99012019,
      "alliance_name": "Can i bring my Drake..."
    },
    "zkb_url": "https://zkillboard.com/kill/129891446/",
    "total_value": 6137682229.45,
    "final_attacker": {
      "character_name": "Daraid Trilnos",
      "corporation_name": "Candy From Stranger",
      "alliance_name": null,
      "ship_type_name": "Gnosis"
    }
  },
  {
    "killmail_id": 129890664,
    "killmail_hash": "75c93f4718d138f60d19161e2132ff1e2daffc15",
    "kill_time": "2025-09-15T11:38:45Z",
    "ship_type_id": 20189,
    "ship_type_name": "Fenrir",
    "solar_system_id": 30005195,
    "solar_system_name": "Vecamia",
    "region_name": "Genesis",
    "victim": {
      "character_id": 1746842877,
      "character_name": "Marcos Arellius",
      "corporation_id": 98809730,
      "corporation_name": "United Warmongers Cooperative",
      "alliance_id": null,
      "alliance_name": null
    },
    "zkb_url": "https://zkillboard.com/kill/129890664/",
    "total_value": 5353218830.82,
    "final_attacker": {
      "character_name": "ScummyB",
      "corporation_name": "Prostate Jackhammer",
      "alliance_name": "Daughters of Ane",
      "ship_type_name": "Praxis"
    }
  },
  {
    "killmail_id": 129886324,
    "killmail_hash": "c5712c472f9a324985e3b0fc90a483737a04dd76",
    "kill_time": "2025-09-15T02:54:08Z",
    "ship_type_id": 20185,
    "ship_type_name": "Charon",
    "solar_system_id": 30005195,
    "solar_system_name": "Vecamia",
    "region_name": "Genesis",
    "victim": {
      "character_id": 2122052050,
      "character_name": "trooperhityou",
      "corporation_id": 98089778,
      "corporation_name": "Black-eyed Bruiser",
      "alliance_id": null,
      "alliance_name": null
    },
    "zkb_url": "https://zkillboard.com/kill/129886324/",
    "total_value": 2618200284.92,
    "final_attacker": {
      "character_name": "Edurardo D'Appaza",
      "corporation_name": "Sons of Seyllin",
      "alliance_name": "Pirate Lords of War",
      "ship_type_name": "Redeemer"
    }
  },
  {
    "killmail_id": 129885760,
    "killmail_hash": "e31dfa01a6d6ca549e150ecd83a1d1afe0ebf4de",
    "kill_time": "2025-09-15T02:11:59Z",
    "ship_type_id": 20185,
    "ship_type_name": "Charon",
    "solar_system_id": 30000241,
    "solar_system_name": "YMJG-4",
    "region_name": "Vale of the Silent",
    "victim": {
      "character_id": 2123340668,
      "character_name": "good school7-1",
      "corporation_id": 98750141,
      "corporation_name": "Comprehensive sales",
      "alliance_id": 99013541,
      "alliance_name": "Fraternity Auxiliary"
    },
    "zkb_url": "https://zkillboard.com/kill/129885760/",
    "total_value": 1974069215.69,
    "final_attacker": {
      "character_name": "Gladius Humanitatis",
      "corporation_name": "The Most Kind Corporation",
      "alliance_name": "The Ancients.",
      "ship_type_name": "Purifier"
    }
  },
  {
    "killmail_id": 129885759,
    "killmail_hash": "68b415b69f6c76c740ed61c6f205875178b1118b",
    "kill_time": "2025-09-15T02:11:51Z",
    "ship_type_id": 20185,
    "ship_type_name": "Charon",
    "solar_system_id": 30000241,
    "solar_system_name": "YMJG-4",
    "region_name": "Vale of the Silent",
    "victim": {
      "character_id": 2123340666,
      "character_name": "good school5-1",
      "corporation_id": 98750141,
      "corporation_name": "Comprehensive sales",
      "alliance_id": 99013541,
      "alliance_name": "Fraternity Auxiliary"
    },
    "zkb_url": "https://zkillboard.com/kill/129885759/",
    "total_value": 1974069215.69,
    "final_attacker": {
      "character_name": "ScramU L Jackson",
      "corporation_name": "Worthless Carebears",
      "alliance_name": "The Initiative.",
      "ship_type_name": "Hound"
    }
  },
  {
    "killmail_id": 129884322,
    "killmail_hash": "2207a4dcc0a0389e6492222f814ea65ea79c11cc",
    "kill_time": "2025-09-15T00:08:11Z",
    "ship_type_id": 28846,
    "ship_type_name": "Nomad",
    "solar_system_id": 30000781,
    "solar_system_name": "0UBC-R",
    "region_name": "Insmother",
    "victim": {
      "character_id": 2112590935,
      "character_name": "Graycon Echerie",
      "corporation_id": 98011082,
      "corporation_name": "Shadow State",
      "alliance_id": 1354830081,
      "alliance_name": "Goonswarm Federation"
    },
    "zkb_url": "https://zkillboard.com/kill/129884322/",
    "total_value": 10276883354.68,
    "final_attacker": {
      "character_name": "mistiks",
      "corporation_name": "Vanishing Point.",
      "alliance_name": "The Initiative.",
      "ship_type_name": "Sabre"
    }
  },
  {
    "killmail_id": 129877190,
    "killmail_hash": "431aeb83c9cf4a8343b819050357f63b0b1c8630",
    "kill_time": "2025-09-14T17:53:15Z",
    "ship_type_id": 20185,
    "ship_type_name": "Charon",
    "solar_system_id": 30002972,
    "solar_system_name": "Gheth",
    "region_name": "Devoid",
    "victim": {
      "character_id": 2113469401,
      "character_name": "Mathus Arkwright",
      "corporation_id": 1000044,
      "corporation_name": "School of Applied Knowledge",
      "alliance_id": null,
      "alliance_name": null
    },
    "zkb_url": "https://zkillboard.com/kill/129877190/",
    "total_value": 9934665118.88,
    "final_attacker": {
      "character_name": "Cannibal Khan",
      "corporation_name": "R.E.M.N.A.N.T.S",
      "alliance_name": null,
      "ship_type_name": "Talos"
    }
  },
  {
    "killmail_id": 129875853,
    "killmail_hash": "e6fe14e2d08b35378129362f9b362c3ec081b87f",
    "kill_time": "2025-09-14T17:09:50Z",
    "ship_type_id": 20185,
    "ship_type_name": "Charon",
    "solar_system_id": 30003125,
    "solar_system_name": "A1-AUH",
    "region_name": "Esoteria",
    "victim": {
      "character_id": 2118938109,
      "character_name": "De Teis Yu",
      "corporation_id": 1000044,
      "corporation_name": "School of Applied Knowledge",
      "alliance_id": null,
      "alliance_name": null
    },
    "zkb_url": "https://zkillboard.com/kill/129875853/",
    "total_value": 2288577410.02,
    "final_attacker": {
      "character_name": "LeggaSchnegge",
      "corporation_name": "Ether Element",
      "alliance_name": "Invidia Gloriae Comes",
      "ship_type_name": "Jackdaw"
    }
  },
  {
    "killmail_id": 129871519,
    "killmail_hash": "d5b0abcd4445f72ecab7e6afed558f8972f21274",
    "kill_time": "2025-09-14T13:50:36Z",
    "ship_type_id": 28850,
    "ship_type_name": "Ark",
    "solar_system_id": 30003525,
    "solar_system_name": "Bagodan",
    "region_name": "Domain",
    "victim": {
      "character_id": 94163972,
      "character_name": "Bert Adam",
      "corporation_id": 98640383,
      "corporation_name": "Swiss Mining and Trading",
      "alliance_id": 99003995,
      "alliance_name": "Invidia Gloriae Comes"
    },
    "zkb_url": "https://zkillboard.com/kill/129871519/",
    "total_value": 9428232676.31,
    "final_attacker": {
      "character_name": "PurgerAdrenaline",
      "corporation_name": "Brazilian Templars",
      "alliance_name": "BLACKFLAG.",
      "ship_type_name": "Khizriel"
    }
  },
  {
    "killmail_id": 129868692,
    "killmail_hash": "3f6829ac2551881c01fc724e8959e98d74c4fedc",
    "kill_time": "2025-09-14T11:37:49Z",
    "ship_type_id": 20185,
    "ship_type_name": "Charon",
    "solar_system_id": 30003125,
    "solar_system_name": "A1-AUH",
    "region_name": "Esoteria",
    "victim": {
      "character_id": 93555898,
      "character_name": "pirate Ellecon",
      "corporation_id": 98626718,
      "corporation_name": "Kuan.Dai.Shan",
      "alliance_id": 99009163,
      "alliance_name": "Dracarys."
    },
    "zkb_url": "https://zkillboard.com/kill/129868692/",
    "total_value": 1973598093.48,
    "final_attacker": {
      "character_name": "Gypsy Fortitude",
      "corporation_name": "State War Academy",
      "alliance_name": null,
      "ship_type_name": "Pacifier"
    }
  }
]